[{"_path":"/portfolio/kostromskoy-terem","_dir":"portfolio","_draft":false,"_partial":false,"_locale":"","title":"Перенос и обслуживание brusovoi.ru","description":"Перенос сайта Костромской терем на Wordpress, адаптивная вёрстка.","thumb":"/img/portfolio/kostromskoyterem/card.jpg","image":"/img/portfolio/kostromskoyterem/card.jpg","year":2020,"cardtitle":"Костромской Терем","menutitle":"костромской-терем.рф","tags":["Перенос","Модернизация","3d проекты"],"url":"https://костромской-терем.рф/","layout":"sites","h1":"Перенос сайта Костромской терем","_type":"markdown","_id":"content:portfolio:kostromskoy-terem.md","_source":"content","_file":"portfolio/kostromskoy-terem.md","_extension":"md","sitemap":{"loc":"/portfolio/kostromskoy-terem"}},{"_path":"/portfolio/masterlesstroi","_dir":"portfolio","_draft":false,"_partial":false,"_locale":"","title":"Создание сайта для компании МЛ-Строй","description":"Создание сайта с нуля, для строительной компании Мастерлесстрой. Проектирование и визуализация проектов для сайта.","thumb":"/img/portfolio/masterlesstroi/card.jpg","image":"/img/portfolio/masterlesstroi/card.jpg","year":2018,"cardtitle":"Мастерлесстрой","menutitle":"masterlesstroi.ru","tags":["Создание","Дизайн","Модернизация","3d проекты"],"url":"https://masterlesstroi.ru/","layout":"sites","h1":"Создание сайта МЛ-Строй","_type":"markdown","_id":"content:portfolio:masterlesstroi.md","_source":"content","_file":"portfolio/masterlesstroi.md","_extension":"md","sitemap":{"loc":"/portfolio/masterlesstroi"}}]