[{"_path":"/portfolio/kostromaplotnik","_dir":"portfolio","_draft":false,"_partial":false,"_locale":"","title":"Создание и обновление сайта kostromaplotnik.ru","description":"Создание и обновление сайта на wordpress. Добавили новые модули.","thumb":"/img/portfolio/kostromaplotnik/card.jpg","image":"/img/portfolio/kostromaplotnik/card.jpg","year":2017,"cardtitle":"Кострома Плотник","menutitle":"kostromaplotnik.ru","tags":["Создание","Дизайн","Модернизация","3d проекты"],"url":"https://kostromaplotnik.ru/","layout":"sites","h1":"Создание и обновление сайта Костромаплотник","_type":"markdown","_id":"content:portfolio:kostromaplotnik.md","_source":"content","_file":"portfolio/kostromaplotnik.md","_extension":"md","sitemap":{"loc":"/portfolio/kostromaplotnik"}},{"_path":"/portfolio/lider-brus","_dir":"portfolio","_draft":false,"_partial":false,"_locale":"","title":"Lider-brus.ru","description":"Сайт для строительной компании Лидер Брус. 3д проекты и продвижение.","thumb":"/img/portfolio/lider-brus/card.jpg","image":"/img/portfolio/lider-brus/thumb.jpeg","year":2022,"cardtitle":"Лидер брус","menutitle":"lider-brus.ru","tags":["Обслуживание","Создание","Дизайн","3d проекты"],"url":"https://lider-brus.ru/","layout":"sites","favorite":true,"h1":"Сайт строительной компании lider-brus.ru","_type":"markdown","_id":"content:portfolio:lider-brus.md","_source":"content","_file":"portfolio/lider-brus.md","_extension":"md","sitemap":{"loc":"/portfolio/lider-brus"}}]